{
    "submission": {
        "ACCESSION-NUMBER": "0001292814-24-001738",
        "TYPE": "IRANNOTICE",
        "PUBLIC-DOCUMENT-COUNT": "1",
        "FILING-DATE": "20240430",
        "DATE-OF-FILING-DATE-CHANGE": "20240430",
        "FILER": {
            "COMPANY-DATA": {
                "CONFORMED-NAME": "TIM S.A.",
                "CIK": "0001826168",
                "ASSIGNED-SIC": "4813",
                "ORGANIZATION-NAME": "06 Technology",
                "IRS-NUMBER": "000000000",
                "STATE-OF-INCORPORATION": "D5",
                "FISCAL-YEAR-END": "1231"
            },
            "FILING-VALUES": {
                "FORM-TYPE": "IRANNOTICE",
                "ACT": "34",
                "FILE-NUMBER": "001-39570",
                "FILM-NUMBER": "24896228"
            },
            "BUSINESS-ADDRESS": {
                "STREET1": "JOAO CABRAL DE MELO NETO AVENUE",
                "STREET2": "850 - NORTH TOWER - 12TH FLOOR",
                "CITY": "RIO DE JANEIRO, RJ",
                "STATE": "D5",
                "ZIP": "22775-057",
                "PHONE": "(55) 21-4109-4167"
            },
            "MAIL-ADDRESS": {
                "STREET1": "JOAO CABRAL DE MELO NETO AVENUE",
                "STREET2": "850 - NORTH TOWER - 12TH FLOOR",
                "CITY": "RIO DE JANEIRO, RJ",
                "STATE": "D5",
                "ZIP": "22775-057"
            }
        }
    },
    "documents": [
        {
            "TYPE": "IRANNOTICE",
            "SEQUENCE": "1",
            "FILENAME": "timb20240430_irannotice.htm",
            "DESCRIPTION": "IRANNOTICE"
        }
    ]
}